[
  {
    "_id": "69f556f0fe21fab1ab2a6cc3",
    "username": "user_C0WTMX",
    "level": 1,
    "skillPoints": 0,
    "skills": {
      "energy": {
        "level": 0,
        "total": 30
      },
      "health": {
        "level": 0,
        "total": 100
      },
      "hunger": {
        "level": 0,
        "total": 4
      },
      "attack": {
        "level": 0,
        "total": 100
      },
      "companies": {
        "level": 0,
        "total": 2
      },
      "entrepreneurship": {
        "level": 0,
        "total": 30
      },
      "production": {
        "level": 0,
        "total": 10
      },
      "criticalChance": {
        "level": 0,
        "total": 10
      },
      "criticalDamages": {
        "level": 0,
        "total": 100
      },
      "armor": {
        "level": 0,
        "total": 0
      },
      "precision": {
        "level": 0,
        "total": 50
      },
      "dodge": {
        "level": 0,
        "total": 0
      },
      "lootChance": {
        "level": 0,
        "total": 5
      },
      "management": {
        "level": 0,
        "total": 4
      }
    },
    "militaryRank": 1,
    "createdAt": "2026-05-02T01:44:16.471Z"
  },
  {
    "_id": "69f32cd1c14a33b34abafcbf",
    "username": "user_JS0PK5",
    "level": 1,
    "skillPoints": 0,
    "skills": {
      "energy": {
        "level": 0,
        "total": 30
      },
      "health": {
        "level": 0,
        "total": 100
      },
      "hunger": {
        "level": 0,
        "total": 4
      },
      "attack": {
        "level": 0,
        "total": 100
      },
      "companies": {
        "level": 0,
        "total": 2
      },
      "entrepreneurship": {
        "level": 0,
        "total": 30
      },
      "production": {
        "level": 0,
        "total": 10
      },
      "criticalChance": {
        "level": 0,
        "total": 10
      },
      "criticalDamages": {
        "level": 0,
        "total": 100
      },
      "armor": {
        "level": 0,
        "total": 0
      },
      "precision": {
        "level": 0,
        "total": 50
      },
      "dodge": {
        "level": 0,
        "total": 0
      },
      "lootChance": {
        "level": 0,
        "total": 5
      },
      "management": {
        "level": 0,
        "total": 4
      }
    },
    "militaryRank": 1,
    "createdAt": "2026-04-30T10:20:01.630Z"
  },
  {
    "_id": "69f219a0a408e091c643a2a8",
    "username": "user_U7DGIZ",
    "level": 1,
    "skillPoints": 0,
    "skills": {
      "energy": {
        "level": 0,
        "total": 30
      },
      "health": {
        "level": 0,
        "total": 100
      },
      "hunger": {
        "level": 0,
        "total": 4
      },
      "attack": {
        "level": 0,
        "total": 100
      },
      "companies": {
        "level": 0,
        "total": 2
      },
      "entrepreneurship": {
        "level": 0,
        "total": 30
      },
      "production": {
        "level": 0,
        "total": 10
      },
      "criticalChance": {
        "level": 0,
        "total": 10
      },
      "criticalDamages": {
        "level": 0,
        "total": 100
      },
      "armor": {
        "level": 0,
        "total": 0
      },
      "precision": {
        "level": 0,
        "total": 50
      },
      "dodge": {
        "level": 0,
        "total": 0
      },
      "lootChance": {
        "level": 0,
        "total": 5
      },
      "management": {
        "level": 0,
        "total": 4
      }
    },
    "militaryRank": 1,
    "createdAt": "2026-04-29T14:45:52.485Z"
  },
  {
    "_id": "69f1fc7ed4aa1539da755197",
    "username": "user_FRC2JP",
    "level": 1,
    "skillPoints": 0,
    "skills": {
      "energy": {
        "level": 0,
        "total": 30
      },
      "health": {
        "level": 0,
        "total": 100
      },
      "hunger": {
        "level": 0,
        "total": 4
      },
      "attack": {
        "level": 0,
        "total": 100
      },
      "companies": {
        "level": 0,
        "total": 2
      },
      "entrepreneurship": {
        "level": 0,
        "total": 30
      },
      "production": {
        "level": 0,
        "total": 10
      },
      "criticalChance": {
        "level": 0,
        "total": 10
      },
      "criticalDamages": {
        "level": 0,
        "total": 100
      },
      "armor": {
        "level": 0,
        "total": 0
      },
      "precision": {
        "level": 0,
        "total": 50
      },
      "dodge": {
        "level": 0,
        "total": 0
      },
      "lootChance": {
        "level": 0,
        "total": 5
      },
      "management": {
        "level": 0,
        "total": 4
      }
    },
    "militaryRank": 1,
    "createdAt": "2026-04-29T12:41:34.551Z"
  },
  {
    "_id": "69f18d539731d66eddc1956f",
    "username": "user_CFDU53",
    "level": 1,
    "skillPoints": 0,
    "skills": {
      "energy": {
        "level": 0,
        "total": 30
      },
      "health": {
        "level": 0,
        "total": 100
      },
      "hunger": {
        "level": 0,
        "total": 4
      },
      "attack": {
        "level": 0,
        "total": 100
      },
      "companies": {
        "level": 0,
        "total": 2
      },
      "entrepreneurship": {
        "level": 0,
        "total": 30
      },
      "production": {
        "level": 0,
        "total": 10
      },
      "criticalChance": {
        "level": 0,
        "total": 10
      },
      "criticalDamages": {
        "level": 0,
        "total": 100
      },
      "armor": {
        "level": 0,
        "total": 0
      },
      "precision": {
        "level": 0,
        "total": 50
      },
      "dodge": {
        "level": 0,
        "total": 0
      },
      "lootChance": {
        "level": 0,
        "total": 5
      },
      "management": {
        "level": 0,
        "total": 4
      }
    },
    "militaryRank": 1,
    "createdAt": "2026-04-29T04:47:15.059Z"
  },
  {
    "_id": "69e91140c1c53a3c5cb0da63",
    "username": "user_0J73A8",
    "level": 1,
    "skillPoints": 0,
    "skills": {
      "energy": {
        "level": 0,
        "total": 30
      },
      "health": {
        "level": 0,
        "total": 100
      },
      "hunger": {
        "level": 0,
        "total": 4
      },
      "attack": {
        "level": 0,
        "total": 100
      },
      "companies": {
        "level": 0,
        "total": 2
      },
      "entrepreneurship": {
        "level": 0,
        "total": 30
      },
      "production": {
        "level": 0,
        "total": 10
      },
      "criticalChance": {
        "level": 0,
        "total": 10
      },
      "criticalDamages": {
        "level": 0,
        "total": 100
      },
      "armor": {
        "level": 0,
        "total": 0
      },
      "precision": {
        "level": 0,
        "total": 50
      },
      "dodge": {
        "level": 0,
        "total": 0
      },
      "lootChance": {
        "level": 0,
        "total": 5
      },
      "management": {
        "level": 0,
        "total": 4
      }
    },
    "militaryRank": 1,
    "createdAt": "2026-04-22T18:19:44.232Z"
  },
  {
    "_id": "69d0dcc0b9d7888537c32266",
    "username": "user_FU5ZDR",
    "level": 1,
    "skillPoints": 0,
    "skills": {
      "energy": {
        "level": 0,
        "total": 30
      },
      "health": {
        "level": 0,
        "total": 100
      },
      "hunger": {
        "level": 0,
        "total": 4
      },
      "attack": {
        "level": 0,
        "total": 100
      },
      "companies": {
        "level": 0,
        "total": 2
      },
      "entrepreneurship": {
        "level": 0,
        "total": 30
      },
      "production": {
        "level": 0,
        "total": 10
      },
      "criticalChance": {
        "level": 0,
        "total": 10
      },
      "criticalDamages": {
        "level": 0,
        "total": 100
      },
      "armor": {
        "level": 0,
        "total": 0
      },
      "precision": {
        "level": 0,
        "total": 50
      },
      "dodge": {
        "level": 0,
        "total": 0
      },
      "lootChance": {
        "level": 0,
        "total": 5
      },
      "management": {
        "level": 0,
        "total": 4
      }
    },
    "militaryRank": 3,
    "createdAt": "2026-04-04T09:41:20.642Z"
  },
  {
    "_id": "69ad3d1a1d11bcdf4f7c0112",
    "username": "Adiksakape05",
    "level": 13,
    "skillPoints": 52,
    "skills": {
      "energy": {
        "level": 0,
        "total": 30
      },
      "health": {
        "level": 0,
        "total": 100
      },
      "hunger": {
        "level": 0,
        "total": 4
      },
      "attack": {
        "level": 3,
        "total": 238
      },
      "companies": {
        "level": 1,
        "total": 3
      },
      "entrepreneurship": {
        "level": 6,
        "total": 60
      },
      "production": {
        "level": 2,
        "total": 16
      },
      "criticalChance": {
        "level": 0,
        "total": 15
      },
      "criticalDamages": {
        "level": 0,
        "total": 112
      },
      "armor": {
        "level": 3,
        "total": 39
      },
      "precision": {
        "level": 5,
        "total": 81
      },
      "dodge": {
        "level": 0,
        "total": 7
      },
      "lootChance": {
        "level": 0,
        "total": 5
      },
      "management": {
        "level": 0,
        "total": 4
      }
    },
    "militaryRank": 39,
    "createdAt": "2026-03-08T09:10:50.977Z"
  },
  {
    "_id": "699f620157e519a2d67ffdaa",
    "username": "MongoKaka",
    "level": 20,
    "skillPoints": 78,
    "skills": {
      "energy": {
        "level": 5,
        "total": 80
      },
      "health": {
        "level": 2,
        "total": 120
      },
      "hunger": {
        "level": 0,
        "total": 4
      },
      "attack": {
        "level": 3,
        "total": 233
      },
      "companies": {
        "level": 4,
        "total": 6
      },
      "entrepreneurship": {
        "level": 4,
        "total": 50
      },
      "production": {
        "level": 5,
        "total": 25
      },
      "criticalChance": {
        "level": 2,
        "total": 25
      },
      "criticalDamages": {
        "level": 1,
        "total": 134
      },
      "armor": {
        "level": 2,
        "total": 21
      },
      "precision": {
        "level": 2,
        "total": 65
      },
      "dodge": {
        "level": 3,
        "total": 17
      },
      "lootChance": {
        "level": 2,
        "total": 9
      },
      "management": {
        "level": 0,
        "total": 4
      }
    },
    "militaryRank": 37,
    "createdAt": "2026-02-25T20:56:33.554Z"
  },
  {
    "_id": "698a8d90c0b91cffed8be5ae",
    "username": "Muammar-al-Fortier",
    "level": 25,
    "skillPoints": 100,
    "skills": {
      "energy": {
        "level": 5,
        "total": 80
      },
      "health": {
        "level": 2,
        "total": 120
      },
      "hunger": {
        "level": 0,
        "total": 4
      },
      "attack": {
        "level": 0,
        "total": 157
      },
      "companies": {
        "level": 7,
        "total": 9
      },
      "entrepreneurship": {
        "level": 6,
        "total": 60
      },
      "production": {
        "level": 6,
        "total": 28
      },
      "criticalChance": {
        "level": 0,
        "total": 15
      },
      "criticalDamages": {
        "level": 0,
        "total": 108
      },
      "armor": {
        "level": 2,
        "total": 21
      },
      "precision": {
        "level": 2,
        "total": 65
      },
      "dodge": {
        "level": 2,
        "total": 12
      },
      "lootChance": {
        "level": 2,
        "total": 9
      },
      "management": {
        "level": 0,
        "total": 4
      }
    },
    "militaryRank": 58,
    "createdAt": "2026-02-10T01:44:48.451Z"
  },
  {
    "_id": "697fea462a2dd3cbd8555472",
    "username": "Hakon",
    "level": 27,
    "skillPoints": 107,
    "skills": {
      "energy": {
        "level": 7,
        "total": 100
      },
      "health": {
        "level": 0,
        "total": 100
      },
      "hunger": {
        "level": 0,
        "total": 4
      },
      "attack": {
        "level": 0,
        "total": 155
      },
      "companies": {
        "level": 8,
        "total": 10
      },
      "entrepreneurship": {
        "level": 3,
        "total": 45
      },
      "production": {
        "level": 8,
        "total": 34
      },
      "criticalChance": {
        "level": 0,
        "total": 12
      },
      "criticalDamages": {
        "level": 0,
        "total": 100
      },
      "armor": {
        "level": 0,
        "total": 5
      },
      "precision": {
        "level": 0,
        "total": 55
      },
      "dodge": {
        "level": 0,
        "total": 5
      },
      "lootChance": {
        "level": 0,
        "total": 5
      },
      "management": {
        "level": 1,
        "total": 6
      }
    },
    "militaryRank": 41,
    "createdAt": "2026-02-02T00:05:26.404Z"
  },
  {
    "_id": "6976adfe8895f42c71af5a08",
    "username": "Christifristi",
    "level": 27,
    "skillPoints": 108,
    "skills": {
      "energy": {
        "level": 0,
        "total": 30
      },
      "health": {
        "level": 2,
        "total": 120
      },
      "hunger": {
        "level": 0,
        "total": 4
      },
      "attack": {
        "level": 0,
        "total": 158
      },
      "companies": {
        "level": 7,
        "total": 9
      },
      "entrepreneurship": {
        "level": 0,
        "total": 30
      },
      "production": {
        "level": 0,
        "total": 10
      },
      "criticalChance": {
        "level": 0,
        "total": 15
      },
      "criticalDamages": {
        "level": 0,
        "total": 127
      },
      "armor": {
        "level": 1,
        "total": 28
      },
      "precision": {
        "level": 3,
        "total": 79
      },
      "dodge": {
        "level": 5,
        "total": 30
      },
      "lootChance": {
        "level": 10,
        "total": 25
      },
      "management": {
        "level": 0,
        "total": 4
      }
    },
    "militaryRank": 64,
    "createdAt": "2026-01-25T23:57:50.883Z"
  },
  {
    "_id": "6915809217a579f225dafff4",
    "username": "DenTwan",
    "level": 28,
    "skillPoints": 111,
    "skills": {
      "energy": {
        "level": 5,
        "total": 80
      },
      "health": {
        "level": 0,
        "total": 100
      },
      "hunger": {
        "level": 0,
        "total": 4
      },
      "attack": {
        "level": 0,
        "total": 165
      },
      "companies": {
        "level": 8,
        "total": 10
      },
      "entrepreneurship": {
        "level": 5,
        "total": 55
      },
      "production": {
        "level": 9,
        "total": 37
      },
      "criticalChance": {
        "level": 0,
        "total": 12
      },
      "criticalDamages": {
        "level": 0,
        "total": 112
      },
      "armor": {
        "level": 0,
        "total": 9
      },
      "precision": {
        "level": 0,
        "total": 55
      },
      "dodge": {
        "level": 0,
        "total": 2
      },
      "lootChance": {
        "level": 0,
        "total": 5
      },
      "management": {
        "level": 0,
        "total": 4
      }
    },
    "militaryRank": 64,
    "createdAt": "2025-11-13T06:54:10.783Z"
  }
]